w_rst/__cls_aide_rst__.py
w_rst/__init__.py
w_rst-1.4.dist-info/LICENSE
w_rst-1.4.dist-info/METADATA
w_rst-1.4.dist-info/WHEEL
w_rst-1.4.dist-info/top_level.txt
w_rst-1.4.dist-info/RECORD
